jigbot
